{
  "meta": {
    "title": "榕江县小微企业金融服务信贷平台",
    "subtitle": "汇集榕江县银行机构小微企业信贷产品，按银行、产品分类、担保方式、融资额度和贷款期限快速查询。",
    "organizer": "国家金融监督管理总局榕江监管支局",
    "updatedAt": "2026-06-29T10:16:06+08:00",
    "sourceFile": "榕江县银行业金融机构小微企业融资产品优选-6.23.xlsx",
    "total": 38,
    "stats": {
      "products": 38,
      "banks": 8
    },
    "filters": {
      "banks": [
        "中国农业发展银行榕江县支行",
        "中国农业银行股份有限公司榕江县支行",
        "中国工商银行股份有限公司榕江支行",
        "中国建设银行股份有限公司榕江支行",
        "中国邮政储蓄银行股份有限公司榕江县支行",
        "榕江县农村信用合作联社",
        "贵州银行股份有限公司榕江支行",
        "贵阳银行股份有限公司榕江支行"
      ],
      "categories": [
        "普惠小微"
      ],
      "guarantees": [
        "不限",
        "保证、抵押、质押",
        "信用",
        "信用/抵押",
        "信用、保证、抵押",
        "信用、抵押",
        "抵押",
        "抵押、保证",
        "担保"
      ],
      "regions": [
        "榕江县"
      ]
    }
  },
  "products": [
    {
      "id": 1,
      "bank": "中国工商银行股份有限公司榕江支行",
      "name": "e企快贷",
      "category": "普惠小微",
      "target": "小微企业",
      "conditions": "信用良好、经营稳定",
      "region": "榕江县",
      "guarantee": "抵押",
      "amount": "3000万",
      "term": "1年-3年",
      "rate": "3.0%-4.0%",
      "process": "客户申请，受理、调查，合同签订，放款",
      "contact": "潘经理/陈经理-0855-6678197",
      "amountMax": 3000.0,
      "termMaxMonths": 36
    },
    {
      "id": 2,
      "bank": "中国工商银行股份有限公司榕江支行",
      "name": "黔旅快贷",
      "category": "普惠小微",
      "target": "辖内景区周边经营良好的住宿企业",
      "conditions": "信用良好、经营稳定",
      "region": "榕江县",
      "guarantee": "信用",
      "amount": "500万",
      "term": "1年-3年",
      "rate": "3.0%-4.0%",
      "process": "客户申请，受理、调查，合同签订，放款",
      "contact": "潘经理/陈经理-0855-6678197",
      "amountMax": 500.0,
      "termMaxMonths": 36
    },
    {
      "id": 3,
      "bank": "中国工商银行股份有限公司榕江支行",
      "name": "种植e贷",
      "category": "普惠小微",
      "target": "农户、合作社、小微企业",
      "conditions": "信用良好、经营稳定",
      "region": "榕江县",
      "guarantee": "信用",
      "amount": "300万",
      "term": "根据产业种植年限确定，最长不超过3年",
      "rate": "3.38%-4.0%",
      "process": "客户申请，受理、调查，合同签订，放款",
      "contact": "潘经理/陈经理-0855-6678197",
      "amountMax": 300.0,
      "termMaxMonths": 36
    },
    {
      "id": 4,
      "bank": "中国工商银行股份有限公司榕江支行",
      "name": "养殖e贷",
      "category": "普惠小微",
      "target": "农户、合作社、小微企业",
      "conditions": "信用良好、经营稳定",
      "region": "榕江县",
      "guarantee": "信用",
      "amount": "300万",
      "term": "根据产业养殖年限确定，最长不超过3年",
      "rate": "3.38%-4.0%",
      "process": "客户申请，受理、调查，合同签订，放款",
      "contact": "潘经理/陈经理-0855-6678197",
      "amountMax": 300.0,
      "termMaxMonths": 36
    },
    {
      "id": 5,
      "bank": "中国工商银行股份有限公司榕江支行",
      "name": "经营快贷",
      "category": "普惠小微",
      "target": "小微企业、个体工商户",
      "conditions": "信用良好、经营稳定",
      "region": "榕江县",
      "guarantee": "信用",
      "amount": "500万",
      "term": "1年",
      "rate": "3.0%起",
      "process": "客户申请，核实，放款",
      "contact": "潘经理/陈经理-0855-6678197",
      "amountMax": 500.0,
      "termMaxMonths": 12
    },
    {
      "id": 6,
      "bank": "中国工商银行股份有限公司榕江支行",
      "name": "烟草e贷",
      "category": "普惠小微",
      "target": "小微企业、个体工商户",
      "conditions": "信用良好、经营稳定",
      "region": "榕江县",
      "guarantee": "信用",
      "amount": "80万",
      "term": "1年",
      "rate": "3.0%起",
      "process": "客户申请，核实，放款",
      "contact": "潘经理/陈经理-0855-6678197",
      "amountMax": 80.0,
      "termMaxMonths": 12
    },
    {
      "id": 7,
      "bank": "中国农业银行股份有限公司榕江县支行",
      "name": "微捷贷",
      "category": "普惠小微",
      "target": "指规模为小型或微型的企业客户，不包括农民专业合作社。",
      "conditions": "1、线上系统审批“微捷贷”业务借款企业及其法定代表人须满足以下基本条件：\n（一）经工商行政管理机关核准登记的企业，法定代表人年龄和持股比例达到准入要求。\n（二）在本行开立结算账户，自愿接受本行信贷和结算监督。\n（三）企业当前无逾期贷款并在本行无已核销业务，已结清债项历史风险分类均为正常类或关注类。\n（四）企业及其法定代表人未被列入全国法院失信被执行人名单。\n（五）企业及其法定代表人不存在强制执行或未被撤销的行政处罚记录。\n（六）企业及其法定代表人的客户洗钱和恐怖融资风险等级为中风险及以下；符合本行制裁风险管理政策；不存在刑事犯罪记录。\n（七）企业及其主要股东、法定代表人、实际控制人、高管等人员未从事违法民间借贷、非法集资、涉黑涉恶、涉电诈及其他非法金融活动。\n（八）符合监管部门及本行关于关系人贷款相关规定。\n（九）本行要求的其他条件。\n2、线下人工审批“微捷贷”业务客户准入条件\n企业及其法定代表人除符合《中国农业银行小微企业信贷业务管理办法》的客户准入基本条件外，还应满足以下条件：\n（一）正常生产经营满1年（含）以上，对于原以个人名义或以其他企业名义经营，企业承接原主营业务，有丰富的生产、销售、从业经验的，允许结合原个人或企业的实际生产经营年限进行准入。\n（二）经营状况良好，前12个月销售收入或上年度销售收入是贷款本息的2倍（含）及以上，具备偿还贷款的能力。\n（三）小型企业客户信用等级在BBB-级（含）以上或信用评分450分以上，微型企业客户信用等级在BB级（含）以上或信用评分350分以上。\n（四）信用状况良好、无欠息、无逾期贷款，借款人及其法定代表人、主要投资人、实际控制人、关键管理人等无不良信用记录或虽然有过不良信用记录，但不良信用记录的产生并非主观恶意且申请本次用信前已全部偿还了不良信用或落实了本行认可的还款计划。\n（五）企业及其法定代表人未被列入全国法院失信被执行人名单。\n（六）企业及其法定代表人不存在强制执行或未被撤销的行政处罚记录。\n（七）企业及其法定代表人的客户洗钱和恐怖融资风险等级为中风险及以下；符合本行制裁风险管理政策；不存在刑事犯罪记录。\n（八）企业及其主要股东、法定代表人、实际控制人、高管等人员未从事违法民间借贷、非法集资、涉黑涉恶、涉电诈及其他非法金融活动。\n（九）符合监管部门及本行关于关系人贷款相关规定。",
      "region": "榕江县",
      "guarantee": "信用",
      "amount": "300万元",
      "term": "1年",
      "rate": "综合考虑贷款风险、成本、综合收益、市场竞争等因素，在符合国家级本行有关规定的情况下，由借贷双方协商合理确定。",
      "process": "客户营销→贷款申请→贷款调查、审查、审批→人工复核→合同签订→贷款发放与支用",
      "contact": "杨岳15121446063",
      "amountMax": 300.0,
      "termMaxMonths": 12
    },
    {
      "id": 8,
      "bank": "中国农业银行股份有限公司榕江县支行",
      "name": "黔担易贷",
      "category": "普惠小微",
      "target": "小微企业法人",
      "conditions": "（一）客户信用等级应在BBB级(含)或信用评分500分(含)以上。\n（二）客户分类为支持类或维持类（无需分类的除外）。\n（三）用信后资产负债率不高于最新一期《企业绩效评价标准值》（国务院国资委统计评价局制定）中所属细分行业良好值。\n（四）上年度经营活动现金流量净额大于零或虽然上年度经营活动现金流量净额小于（或等于）零但最近三年经营活动现金流量净额之和大于零且预计现金流状况向好（经营期不足两个会计年度的客户除外）。\n（五）无不良信用记录（含其他金融机构不良信用记录及债券违约等），或虽然有过不良信用记录，但不良信用记录的产生并非由于主观恶意且申请本次用信前已全部偿还了不良信用。\n（六）客户承诺偿还农业银行信用前不再将资产抵（质）押给除农业银行之外的第三方，行业重点客户、总行级核心客户（包括集团本部及其直接或间接控股50%及以上的子公司，或拥有实际控制权的上市公司及其控制的子公司，下同）除外。\n（七）在本行无风险预警信息或者风险预警信息的产生非主观恶意且处置完成并经客户部门确认不存在实质风险。\n（八）近两个会计年度连续亏损（经营期不足两个完整会计年度的客户除外）或在金融机构贷款（含债券等）违约或存在重大风险的法人客户不得办理。\n（九）不得向关系人发放批量担保项下的“黔担易贷”款。\n（十）企业及其法定代表人的客户洗钱和恐怖融资风险等级为中风险及以下；符合本行制裁风险管理政策；不存在刑事犯罪记录。\n（十一）企业及其主要股东、法定代表人、实际控制人、高管等人员未从事违法民间借贷、非法集资、涉黑涉恶、涉电诈及其他非法金融活动。\n（十二）本行其他政策、制度要求的条件。",
      "region": "榕江县",
      "guarantee": "担保",
      "amount": "1000万元",
      "term": "1年",
      "rate": "贷款利率定价实行参数化管理，综合考虑客户资质、贷款成本、风险覆盖、合理收益等因素，根据中国农业银行利率管理有关规定，确定贷款利率。",
      "process": "执行一般法人信贷业务审批流程，包括受理、调查、审查、审批、用信管理和存续期管理等业务环节。",
      "contact": "杨岳15121446063",
      "amountMax": 1000.0,
      "termMaxMonths": 12
    },
    {
      "id": 9,
      "bank": "中国农业银行股份有限公司榕江县支行",
      "name": "抵押e贷",
      "category": "普惠小微",
      "target": "以中国农业银行（以下简称本行）认可的优质房产抵押作为主要担保方式，对符合条件的小微企业（不含个体工商户、农民专业合作社）办理的在线抵押贷款业务。",
      "conditions": "（一）实际控制人（自然人借款人）。\n1.年满18周岁且不超过70周岁。\n2.信用状况正常，在本行及他行无不良信用记录，或虽然有过不良信用记录，但不良信用记录的产生并非由于主观恶意且申请本次用信前已全部偿还了不良信用。\n3.未被列入失信被执行人名单，未被列入严重违法失信人名单。\n4.不存在强制执行或未被撤销的行政处罚记录。\n5.客户洗钱和恐怖融资风险等级为中风险及以下；符合本行制裁风险管理政策；不存在刑事犯罪记录。\n6.未违法从事民间借贷、非法集资、涉黑涉恶、涉赌、涉毒、涉电诈及其他非法金融活动。\n7.符合监管部门及本行关于关系人贷款相关规定。\n8.本行要求的其他条件。\n（二）小微企业（企业借款人）。\n1.生产经营1年（含）以上，对于园区招商引进的入园新注册企业（原企业资产注入新企业的）、个转企企业，允许将原企业或个体经营年限一并纳入计算。\n2.依法设立并持有有效的营业执照、组织机构代码证、税务登记证（若客户已更换“三证合一”营业执照或“五证合一”营业执照，仅需营业执照），特殊行业或按规定应取得环保许可的，还应持有有权部门的相应批准文件或证明。\n3.生产经营合法合规，符合营业执照范围，符合国家产业、环保等相关政策、监管规定和本行信贷政策。\n4.在本行开立结算账户，自愿接受本行信贷和结算监督。\n5.企业信用状况正常，在本行及他行无不良信用记录，或虽然有过不良信用记录，但不良信用记录的产生并非由于主观恶意且申请本次用信前已全部偿还了不良信用。\n6.未被列入失信被执行人名单、未被列入严重违法失信人名单。\n7.不存在欠税、强制执行或未被撤销的行政处罚记录。\n8.客户洗钱和恐怖融资风险等级为中风险及以下；符合本行制裁风险管理政策；不存在刑事犯罪记录。\n9.企业及其主要股东、法定代表人、高管等人员未违法从事民间借贷、非法集资、涉黑涉恶、涉赌、涉毒、涉电诈及其他非法金融活动。\n10.不属于房地产业、金融业。\n11.符合监管部门及本行关于关系人贷款相关规定。\n12.本行要求的其他条件。",
      "region": "榕江县",
      "guarantee": "抵押",
      "amount": "1000万元",
      "term": "单笔贷款期限最长3年，额度有效期最长5年",
      "rate": "综合考虑贷款风险、成本、综合收益、市场竞争等因素，在符合国家及本行有关规定的情况下由借贷双方协商合理确定。",
      "process": "客户营销-贷款申请-贷款调查-贷款审查-贷款审批-用信管理及存续期管理",
      "contact": "杨岳15121446063",
      "amountMax": 1000.0,
      "termMaxMonths": 60
    },
    {
      "id": 10,
      "bank": "中国农业银行股份有限公司榕江县支行",
      "name": "惠企易贷-电费贷",
      "category": "普惠小微",
      "target": "形成集聚效应的特色工业园区、特色产业集群、农业产业化龙头企业、专业市场等优质小微企业客群，以及其他符合本规程的优质小微企业客户。",
      "conditions": "（一）正常生产经营满2年及以上，依法设立并持有有效的营业执照；持有有效的开户许可证、机构信用代码证及中征码（按照国家规定不需要持有相关证照的除外）；申请信用符合公司章程或合伙协议等企业内部规章。\n（二）企业主营业务集中在设备制造、化工、消费品加工、能源与冶炼业，近２年主营业务未发生变更。企业开工用电量基本稳定，近1年用电量下降幅度较上年不超过30%。\n（三）经营状况良好，有实际固定的生产经营场所，有稳定的经营收入，有合法合规、真实合理的融资需求和用途，具备到期偿还本息的能力。\n（四）企业已在我行开立基本账户或结算账户，自愿接受本行信用监督、结算监督、反洗钱监督和反欺诈监督；承诺将我行账户作为企业缴纳电费账户。\n（五）企业符合“上年度盈利、上年度营业收入实现增长、近3年中至少2年营业收入实现增长”三个条件之一。\n（六）小型企业客户信用等级在BBB-级（含）以上或信用评分450分以上，微型企业客户信用等级在BB级（含）以上或信用评分350分以上。\n（七）上年度纳税等级在B级（含）以上。\n（八）借款企业当前不存在未处理的环保处罚，符合国家产业、环保等相关政策，不属于普惠信贷政策指引“禁止介入领域”和“环境和社会风险客户”。特殊行业或按规定应取得环保许可的，还应持有有权部门的相应批准文件或证明。\n（九）借款人及其法定代表人、主要投资人、实际控制人和关键管理人无不良信用记录，或虽有过不良信用记录，但不良信用记录的产生并非主观恶意且申请本次用信前已全部偿还了不良信用或落实了本行认可的还款计划。\n（十）借款人及其主要股东、法定代表人、实际控制人、关键管理人等人员未违法从事民间借贷、非法集资、涉黑涉恶及其他非法金融活动，无欠税、失信被执行、行政处罚记录，或虽有过相关记录，但记录的产生并非主观恶意且申请本次用信前已经偿还欠税或记录已被撤销。\n（十）借款人及其主要股东、法定代表人、实际控制人、受益所有人、高管等关联方未从事洗钱等非法金融活动；借款人及借款人的法定代表人、受益所有人的洗钱风险等级为中风险及以下；符合本行制裁风险管理规定。",
      "region": "榕江县",
      "guarantee": "信用",
      "amount": "500万元",
      "term": "3年",
      "rate": "综合考虑贷款风险、成本、综合收益、市场竞争等因素，在符合国家级本行有关规定的情况下，由借贷双方协商合理确定。",
      "process": "执行一般法人信贷业务审批流程，包括受理、调查、审查、审批、用信管理和存续期管理等业务环节。",
      "contact": "杨岳15121446063",
      "amountMax": 500.0,
      "termMaxMonths": 36
    },
    {
      "id": 11,
      "bank": "中国农业银行股份有限公司榕江县支行",
      "name": "科技e贷",
      "category": "普惠小微",
      "target": "（一）由各级工信部门评选，在名单有效期内，具有“专业化、精细化、特色化、新颖化”特征的排头兵企业，可分为专精特新“小巨人”企业、专精特新中小企业和创新型中小企业。\n（二）国家级、省级、副省级城市高新技术企业。\n（三）全国科技型中小企业信息库中的科技型企业。\n（四）行业属于国家重点支持的高新技术领域（《国家重点支持的高新技术领域》（国科发火〔2008〕172号）明确大类领域包括：电子信息技术、生物与新医药技术、航空航天技术、新材料技术、高技术服务业、新能源及节能技术、资源与环境技术、高新技术改造传统产业等），研发投入总额超过销售收入总额的5%，近三年营业收入年增速不低于10%，拥有核心技术或知识产权的企业。\n（五）高层次人才为企业原始股东（持股比例不低于20%）、法定代表人或实际控制人。高层次人才的具体认定标准为：\n1.国家级人才：包括国际大奖获得者、国家最高科学技术奖项获得者、中国科学院院士、中国工程院院士以及国家主管部委评选认定的人才计划清单内人员，如“万人计划”、“长江学者”、“青年长江学者”等；\n2.省级人才：包括各省人才引进计划人才，省属主管机构评选认定的人才清单内人员。",
      "conditions": "（一）小型企业客户信用等级在BBB-级（含）以上或信用评分450分以上，微型企业客户信用等级在BB级（含）以上或信用评分350分以上。\n（二）企业的经营年限在2年（含）以上。对于原以个人名义或以其他企业名义经营，企业承接原主营业务，有丰富的生产、销售、从业经验的，可结合原个人或企业的实际生产经营年限进行准入。\n（三）科技型企业资质在政府或有权部门批准的有效期内，不得为被政府或有权部门取消科技型企业资质的客户办理业务。\n（四）经有权部门批准成立，有固定生产经营场所，生产经营合法合规，符合国家产业、行业、环保政策。\n（五）借款人及其法定代表人、主要投资人、实际控制人、关键管理人无不良信用记录，或虽然有过不良信用记录，但不良信用记录的产生并非主观恶意且申请本次用信前已全部偿还了不良信用或落实了本行认可的还款计划。\n（六）拥有1项及以上重大或I类知识产权或2项及以上Ⅱ类知识产权（具体标准详见《中国农业银行企业科技创新能力评价体系（试行）》）。\n（七）科技成果已具备产业化生产条件，产品和服务有较强的市场竞争力和成长性，已形成经营性现金流入或取得有效订单。\n（八）科研团队稳定、创新能力强，近12个月研发经费占营业收入比重超过3%。\n（九）借款人及其主要股东、法定代表人、实际控制人、高管等人员未违法从事民间借贷、非法集资、涉黑涉恶及其他非法金融活动。\n（十）借款人及其主要股东、法定代表人、实际控制人、受益所有人、高管等关联方未从事洗钱等非法金融活动；借款人及借款人的法定代表人、受益所有人的洗钱风险等级为中风险及以下；符合本行制裁风险管理规定。\n（十一）符合监管部门及本行关于关系人贷款相关规定。\n（十二）以信用方式用信的，借款人不能为本行关系人，除满足上述条件外，还应同时符合以下条件之一：\n1.采用政府性融资担保公司保证担保或政府风险补偿基金增信，且本行风险分担比例不高于40%。\n2.信用等级在BBB级（含）以上或信用评分在500分（含）以上，且近2年主营业务收入或净利润的平均增长率达到5%以上。\n3.国家部委及省级政府机构认定的“瞪羚”企业、“隐形冠军”企业。\n4.专精特新“小巨人”企业或专精特新中小企业。\n5.本行子公司及相关基金投资的科技型小微企业。\n6.近12个月有清科集团公布的中国创业投资机构榜单前10名投资机构入股的科技型小微企业（贷款申请前已撤资的除外）。\n7.省级或副省级城市及以上政府性投资（引导）基金入股的科技型小微企业。\n8.在本行已采用房地产抵押且增加信用方式额度后合计用信不超过房地产评估值90%的科技型小微企业。",
      "region": "榕江县",
      "guarantee": "信用/抵押",
      "amount": "1000万元",
      "term": "3年",
      "rate": "贷款利率定价实行参数化管理，综合考虑客户资质、贷款成本、风险覆盖、合理收益等因素，根据中国农业银行利率管理有关规定，确定贷款利率。",
      "process": "执行一般法人信贷业务审批流程，包括受理、调查、审查、审批、用信管理和存续期管理等业务环节。",
      "contact": "杨岳15121446063",
      "amountMax": 1000.0,
      "termMaxMonths": 36
    },
    {
      "id": 12,
      "bank": "中国农业银行股份有限公司榕江县支行",
      "name": "惠农e贷",
      "category": "普惠小微",
      "target": "小微企业、个体工商户",
      "conditions": "（一）年龄在18周岁（含）以上，且申请贷款时年龄和贷款期限之和最长不超过70年。\n（二）符合农户贷款信用评分准入标准。\n（三）具有一年（含）以上相关行业从业经验，且能提供合法、足值、有效的押品。\n（四）借款人及其配偶信用状况良好，征信报告中无以下不良信用记录：\n1.申请贷款时存在逾期贷款或逾期信用卡透支；\n2.最近24个月内存在连续3期以上或累计6期以上的逾期记录；\n3.存在呆账或未结清的被追偿情况；\n4.存在欠税、强制执行、未被撤销的行政处罚记录；\n5.担保的贷款五级分类存在“正常”以外的状态。\n（五）借款人及其家庭成员无逃废债务、从事非法民间借贷、非法集资、涉黑涉恶行为及其他非法活动的行为，未列入相关部门公布的失信名单。\n（六）符合本行反洗钱、反恐怖融资、反扩散融资、反逃税及制裁风险管理（以下简称反洗钱）相关规定。\n（七）符合本行关联交易和关系人贷款管理相关规定。\n（八）不属于公务员或事业单位员工。\n（九）贷款行规定的其他条件。",
      "region": "榕江县",
      "guarantee": "信用/抵押",
      "amount": "1000万元",
      "term": "5年",
      "rate": "根据综合借款人资质、管理成本、风险水平、同业定价等因素确定贷款利率。",
      "process": "受理、调查、审查、审批、用信管理和存续期管理等业务环节。",
      "contact": "杨岳15121446063",
      "amountMax": 1000.0,
      "termMaxMonths": 60
    },
    {
      "id": 13,
      "bank": "中国农业银行股份有限公司榕江县支行",
      "name": "商户e贷",
      "category": "普惠小微",
      "target": "符合贷款准入条件、从事生产经营活动的个人客户（含农户身份），包括但不限于银联模型客户、房贷模型客户、金融资产模型客户、预授信客户、分行特色互联网经营场景客户等。",
      "conditions": "（一）借款人为具有完全民事行为能力，持有合法有效身份证件的中华人民共和国公民。申请签约时年满20周岁且小于65周岁。\n（二）本行电子银行客户，经过本行有效安全身份认证。\n（三）信用状况良好，符合《中国农业银行个人信贷业务管理办法》相关规定。\n（四）信用评分符合准入规定。\n（五）预期收入稳定或拥有足够价值的资产收益，具备按期偿还信用的能力。\n（六）具有营业执照、有权批准部门颁发的生产经营资质许可证或其他合法有效经营证明。\n（七）贷款用途具体、明确、合理。\n（八）符合反洗钱有关规定，符合监管及本行关联交易、关系人贷款管理相关规定。\n（九）未违法从事民间借贷、非法集资、涉黑涉恶及其他非法金融活动。\n（十）不属于公务员、军人、事业单位工作人员、银行员工等不得从事或参与营利性活动的人员，国家或地方政府另有政策支持的除外。\n（十一）外部监管部门和本规定的其他条件。",
      "region": "榕江县",
      "guarantee": "信用",
      "amount": "300万",
      "term": "5年",
      "rate": "综合考虑客户资质、贷款成本、风险覆盖、合理收益等因素，实施差异化定价管理，具体按照总行利率政策的相关规定执行。",
      "process": "受理、调查、审查、审批、用信管理和存续期管理等业务环节。",
      "contact": "杨岳15121446063",
      "amountMax": 300.0,
      "termMaxMonths": 60
    },
    {
      "id": 14,
      "bank": "中国建设银行股份有限公司榕江支行",
      "name": "商叶云贷（订烟数据）——针对烟草客群",
      "category": "普惠小微",
      "target": "个体工商户、个人独资企业、小微企业",
      "conditions": "持有当地烟草专卖局签发的《烟草专卖零售许可证》且许可证剩余有效期在3个月（含）以上，近12个月至少6个月（含）有订烟记录，企业及企业主征信良好。",
      "region": "榕江县",
      "guarantee": "信用",
      "amount": "200万元",
      "term": "最长36个月",
      "rate": "3.05%起",
      "process": "可通过各类电子渠道，包括建设银行网上银行、 “建行惠懂你”APP自助申请贷款。",
      "contact": "杨昌林、龙胜鑫0855-6620957",
      "amountMax": 200.0,
      "termMaxMonths": 36
    },
    {
      "id": 15,
      "bank": "中国建设银行股份有限公司榕江支行",
      "name": "商户云贷",
      "category": "普惠小微",
      "target": "个体工商户、个人独资企业、小微企业",
      "conditions": "成立一年以上，在建行开立个人或对公结算账户，有收单数据，企业及企业主征信良好。",
      "region": "榕江县",
      "guarantee": "信用",
      "amount": "300万元",
      "term": "最长36个月",
      "rate": "3.05%起",
      "process": "可通过各类电子渠道，包括建设银行网上银行、 “建行惠懂你”APP自助申请贷款。",
      "contact": "杨昌林、龙胜鑫0855-6620957",
      "amountMax": 300.0,
      "termMaxMonths": 36
    },
    {
      "id": 16,
      "bank": "中国建设银行股份有限公司榕江支行",
      "name": "个人经营信用快贷",
      "category": "普惠小微",
      "target": "个体工商户、个人独资企业、小微企业",
      "conditions": "在建行开立个人结算账户，账户交易好，企业及企业主征信良好。",
      "region": "榕江县",
      "guarantee": "信用",
      "amount": "300万元",
      "term": "最长36个月",
      "rate": "3.05%起",
      "process": "可通过各类电子渠道，包括建设银行网上银行、手机银行、“建行惠懂你”APP、官方网站、善融商务平台、智慧柜员机等自助设备自助申请贷款。",
      "contact": "杨昌林、龙胜鑫0855-6620957",
      "amountMax": 300.0,
      "termMaxMonths": 36
    },
    {
      "id": 17,
      "bank": "中国建设银行股份有限公司榕江支行",
      "name": "个体工商户抵押快贷",
      "category": "普惠小微",
      "target": "个体工商户、个人独资企业、小微企业",
      "conditions": "企业成立一年以上（成立不满1年的但满3个月（含）的，应提供交易流水或缴税记录或水电气缴费等可证明生产经营的材料），提供商品房、自建房等为抵押物。",
      "region": "榕江县",
      "guarantee": "信用",
      "amount": "500万元",
      "term": "最长10年",
      "rate": "3.05%起",
      "process": "可通过各类电子渠道，包括建设银行网上银行、手机银行、“建行惠懂你”APP、官方网站、善融商务平台、智慧柜员机等自助设备自助申请贷款。",
      "contact": "杨昌林、龙胜鑫0855-6620957",
      "amountMax": 500.0,
      "termMaxMonths": 120
    },
    {
      "id": 18,
      "bank": "中国建设银行股份有限公司榕江支行",
      "name": "小微快贷",
      "category": "普惠小微",
      "target": "小微企业",
      "conditions": "在建行开立对公结算账户，账户交易好，企业及企业主征信良好。",
      "region": "榕江县",
      "guarantee": "信用",
      "amount": "300万元",
      "term": "最长36个月",
      "rate": "3.05%起",
      "process": "企业主提供了营业执照、身份证、征信查询授权书、房产证等基本资料至建行即可申请。",
      "contact": "杨昌林、龙胜鑫0855-6620957",
      "amountMax": 300.0,
      "termMaxMonths": 36
    },
    {
      "id": 19,
      "bank": "中国建设银行股份有限公司榕江支行",
      "name": "抵押快贷",
      "category": "普惠小微",
      "target": "小微企业",
      "conditions": "企业成立一年以上（成立不满1年的但满3个月（含）的，至少有一次缴税记录），提供商品房、自建房等为抵押物。",
      "region": "榕江县",
      "guarantee": "信用",
      "amount": "500万元",
      "term": "最长10年",
      "rate": "3.05%起",
      "process": "企业主提供了营业执照、身份证、征信查询授权书、房产证等基本资料至建行即可申请。",
      "contact": "杨昌林、龙胜鑫0855-6620957",
      "amountMax": 500.0,
      "termMaxMonths": 120
    },
    {
      "id": 20,
      "bank": "中国建设银行股份有限公司榕江支行",
      "name": "云税贷",
      "category": "普惠小微",
      "target": "小微企业",
      "conditions": "企业诚信纳税，纳税等级为A、B、M级，成立2年（含）以上（M级客户除外），近12个月纳税总额5000元（含）以上（M级客户除外）。",
      "region": "榕江县",
      "guarantee": "信用",
      "amount": "200万元",
      "term": "最长36个月",
      "rate": "3.05%起",
      "process": "在建设银行开立对公账户后，在网银、手机银行、“建行惠懂你”手机APP等渠道自助申请办理。",
      "contact": "杨昌林、龙胜鑫0855-6620957",
      "amountMax": 200.0,
      "termMaxMonths": 36
    },
    {
      "id": 21,
      "bank": "中国建设银行股份有限公司榕江支行",
      "name": "薪金云贷",
      "category": "普惠小微",
      "target": "小微企业",
      "conditions": "企业诚信经营，在建行稳定代发工资或公积金缴交诚信，贷款额度综合考虑企业纳税情况（含减税额）、企业纳税信用等级、企业及企业主与建设银行合作情况等因素确定。",
      "region": "榕江县",
      "guarantee": "信用",
      "amount": "300万元",
      "term": "最长36个月",
      "rate": "3.05%起",
      "process": "在建设银行开立对公账户后，在网银、 “建行惠懂你”手机APP等渠道自助申请办理。",
      "contact": "杨昌林、龙胜鑫0855-6620957",
      "amountMax": 300.0,
      "termMaxMonths": 36
    },
    {
      "id": 22,
      "bank": "中国邮政储蓄银行股份有限公司榕江县支行",
      "name": "产业贷信用",
      "category": "普惠小微",
      "target": "个体工商户以及法人股东",
      "conditions": "信用良好、经营稳定",
      "region": "榕江县",
      "guarantee": "信用",
      "amount": "100万元",
      "term": "4年",
      "rate": "3.7%起",
      "process": "客户申请→受理、调查、审批→合同签订→放款",
      "contact": "龙宝明13017428111",
      "amountMax": 100.0,
      "termMaxMonths": 48
    },
    {
      "id": 23,
      "bank": "中国邮政储蓄银行股份有限公司榕江县支行",
      "name": "极速贷信用",
      "category": "普惠小微",
      "target": "个体工商户以及法人股东",
      "conditions": "信用良好、经营稳定",
      "region": "榕江县",
      "guarantee": "信用",
      "amount": "100万元",
      "term": "5年",
      "rate": "3.1%起",
      "process": "客户申请→受理、调查、审批→合同签订→放款",
      "contact": "龙宝明13017428111",
      "amountMax": 100.0,
      "termMaxMonths": 60
    },
    {
      "id": 24,
      "bank": "中国邮政储蓄银行股份有限公司榕江县支行",
      "name": "极速贷抵押",
      "category": "普惠小微",
      "target": "个体工商户以及法人股东",
      "conditions": "信用良好、经营稳定",
      "region": "榕江县",
      "guarantee": "抵押",
      "amount": "1000万元",
      "term": "10年",
      "rate": "3.1%起",
      "process": "客户申请→受理、调查、审批→合同签订→放款",
      "contact": "龙宝明13017428111",
      "amountMax": 1000.0,
      "termMaxMonths": 120
    },
    {
      "id": 25,
      "bank": "中国邮政储蓄银行股份有限公司榕江县支行",
      "name": "小微易贷",
      "category": "普惠小微",
      "target": "企业",
      "conditions": "信用良好、经营稳定",
      "region": "榕江县",
      "guarantee": "信用、抵押",
      "amount": "1000万元",
      "term": "2年",
      "rate": "3.45%起",
      "process": "客户申请→受理、调查、审批→合同签订→放款",
      "contact": "吴长生18386731557",
      "amountMax": 1000.0,
      "termMaxMonths": 24
    },
    {
      "id": 26,
      "bank": "中国邮政储蓄银行股份有限公司榕江县支行",
      "name": "区域特色小企业贷款",
      "category": "普惠小微",
      "target": "企业",
      "conditions": "信用良好、经营稳定",
      "region": "榕江县",
      "guarantee": "抵押、保证",
      "amount": "3000万元",
      "term": "5年",
      "rate": "3.45%起",
      "process": "客户申请→受理、调查、审批→合同签订→放款",
      "contact": "吴长生18386731557",
      "amountMax": 3000.0,
      "termMaxMonths": 60
    },
    {
      "id": 27,
      "bank": "贵州银行股份有限公司榕江支行",
      "name": "结算贷",
      "category": "普惠小微",
      "target": "小微企业、个体工商户",
      "conditions": "持续经营满1年，信用良好。",
      "region": "榕江县",
      "guarantee": "信用",
      "amount": "授信额度原则上不超过100万元",
      "term": "以企业为授信对象的，授信期限最长不超过3年（含）、以自然人为授信对象的，授信期限最长不超过5年（含）",
      "rate": "4%-5%",
      "process": "客户申请，银行受理，调查，审批，合同签订，放款。",
      "contact": "潘经理0855-6677573",
      "amountMax": 100.0,
      "termMaxMonths": 60
    },
    {
      "id": 28,
      "bank": "贵州银行股份有限公司榕江支行",
      "name": "税易贷",
      "category": "普惠小微",
      "target": "小微企业、个体工商户",
      "conditions": "纳税等级A,B,M,C级及以上。持续经营满2年，信用良好。。",
      "region": "榕江县",
      "guarantee": "信用、保证、抵押",
      "amount": "线上最高300万元、线下最高500万元",
      "term": "授信期限最长不超过1年（含）",
      "rate": "3.1%-5%",
      "process": "客户申请，银行受理，调查，审批，合同签订，放款。",
      "contact": "潘经理0855-6677573",
      "amountMax": 500.0,
      "termMaxMonths": 12
    },
    {
      "id": 29,
      "bank": "贵州银行股份有限公司榕江支行",
      "name": "小微经营快贷",
      "category": "普惠小微",
      "target": "小微企业主、个体工商户、专业大户、专业农场、农民专业合作社、农业龙头企业等",
      "conditions": "持续经营满1年，信用良好。",
      "region": "榕江县",
      "guarantee": "信用、保证、抵押",
      "amount": "授信额度原则上不超过1000万元",
      "term": "期限1年，最长不超过3年",
      "rate": "3.1%-5%",
      "process": "客户申请，银行受理，调查，审批，合同签订，放款。",
      "contact": "潘经理0855-6677573",
      "amountMax": 1000.0,
      "termMaxMonths": 36
    },
    {
      "id": 30,
      "bank": "贵阳银行股份有限公司榕江支行",
      "name": "爽农诚意贷",
      "category": "普惠小微",
      "target": "个体工商户及小微企业主",
      "conditions": "1、申请人至少正在经营一年，且持有有效的营业执照或行业资质；2、借款人需为农户；3、借款人征信记录良好、无不良记录。",
      "region": "榕江县",
      "guarantee": "信用",
      "amount": "最高30万元",
      "term": "最长5年",
      "rate": "同期LPR起",
      "process": "1、借款人可以通过我行手机银行或线下发起申请；2、我行接件收集相关经营资料后开始走内部审批流程，若审批通过则可以在我行手机银行签约授信并用信。",
      "contact": "吴经理0855-2260086",
      "amountMax": 30.0,
      "termMaxMonths": 60
    },
    {
      "id": 31,
      "bank": "贵阳银行股份有限公司榕江支行",
      "name": "烟商e贷",
      "category": "普惠小微",
      "target": "个体工商户",
      "conditions": "1、本人名下持有烟证且本人持有营业执照（需为个体工商户）；2、持有烟证至少满3个月（含）以上；3、征信记录良好、无不良记录。",
      "region": "榕江县",
      "guarantee": "信用",
      "amount": "最高100万元",
      "term": "1年",
      "rate": "同期LPR起",
      "process": "1、通过我行微信公众号、手机银行及我行客户经理营销二维码进行线上申请，根据提示录入基本信息；2、申请时需扫码申请人身份证原件及营业执照原件；3、提交后半个小时内出审批结合，纯线上申请、授信及用信，方便又快捷。",
      "contact": "吴经理0855-2260086",
      "amountMax": 100.0,
      "termMaxMonths": 12
    },
    {
      "id": 32,
      "bank": "贵阳银行股份有限公司榕江支行",
      "name": "税源e贷",
      "category": "普惠小微",
      "target": "个体工商户及小微企业主",
      "conditions": "1、完整纳税1年以上，且纳税等级至少达到M级以上；2、征信记录良好、无不良记录；3、申请人持股至少达到20%（含）以上。",
      "region": "榕江县",
      "guarantee": "信用、抵押",
      "amount": "最高1000万元",
      "term": "1年",
      "rate": "同期LPR起",
      "process": "1、通过我行微信公众号、手机银行及我行客户经理营销二维码进行线上申请，根据提示录入基本信息；2、申请时需扫码申请人身份证原件及营业执照原件；3、提交后半个小时内出审批结合，100万元以内纯线上申请、授信及用信，方便又快捷。",
      "contact": "吴经理0855-2260086",
      "amountMax": 1000.0,
      "termMaxMonths": 12
    },
    {
      "id": 33,
      "bank": "贵阳银行股份有限公司榕江支行",
      "name": "诚e贷",
      "category": "普惠小微",
      "target": "个体工商户及小微企业主",
      "conditions": "1、借款人在本地有住房或纳税等级达到B级以上；",
      "region": "榕江县",
      "guarantee": "信用",
      "amount": "最高50万元",
      "term": "1年",
      "rate": "同期LPR起",
      "process": "1、借款人可以通过我行手机银行或线下发起申请；2、我行接件收集相关经营资料后开始走内部审批流程，若审批通过则可以在我行手机银行签约授信并用信。",
      "contact": "吴经理0855-2260086",
      "amountMax": 50.0,
      "termMaxMonths": 12
    },
    {
      "id": 34,
      "bank": "榕江县农村信用合作联社",
      "name": "“致富通”农户小额信用贷款",
      "category": "普惠小微",
      "target": "农户",
      "conditions": "借款人在18周岁（含）以上至65周岁（含），信用良好，经营稳定",
      "region": "榕江县",
      "guarantee": "信用",
      "amount": "30万元",
      "term": "3年",
      "rate": "5.0%-8.0%",
      "process": "客户申请→受理→调查→审批→合同签订→贷款发放。",
      "contact": "杨经理0855-6621605",
      "amountMax": 30.0,
      "termMaxMonths": 36
    },
    {
      "id": 35,
      "bank": "榕江县农村信用合作联社",
      "name": "易贷通·榕易贷",
      "category": "普惠小微",
      "target": "居民+个体工商户+小微企业主+单位职工",
      "conditions": "信用良好，经营稳定",
      "region": "榕江县",
      "guarantee": "信用",
      "amount": "50万元",
      "term": "3年",
      "rate": "3.0%-8.0%",
      "process": "客户申请→受理→调查→审批→合同签订→贷款发放。",
      "contact": "杨经理0855-6621605",
      "amountMax": 50.0,
      "termMaxMonths": 36
    },
    {
      "id": 36,
      "bank": "榕江县农村信用合作联社",
      "name": "黔农·农惠贷（脱贫人口小额信贷）",
      "category": "普惠小微",
      "target": "建档立卡脱贫人口和边缘易致贫人口",
      "conditions": "农信社评定信用等级在“普惠级”（含）以上,有必要的劳动生产技能和一定还款能力;用途合法且有一定市场前景;借款人年龄原则上应在18周岁(含)至65 周岁(含)之间。",
      "region": "榕江县",
      "guarantee": "信用",
      "amount": "10万",
      "term": "3年",
      "rate": "3.0%-3.4%",
      "process": "申请→当地乡村振兴主管部门审核推荐→建档评级授信并审核贷款用途→贷款发放",
      "contact": "杨经理0855-6621605",
      "amountMax": 10.0,
      "termMaxMonths": 36
    },
    {
      "id": 37,
      "bank": "榕江县农村信用合作联社",
      "name": "兴业贷",
      "category": "普惠小微",
      "target": "个人+合作社",
      "conditions": "信用良好，经营稳定",
      "region": "榕江县",
      "guarantee": "不限",
      "amount": "500万元",
      "term": "3年",
      "rate": "5.0%-8.0%",
      "process": "客户申请→受理→调查→审批→合同签订→贷款发放。",
      "contact": "杨经理0855-6621605",
      "amountMax": 500.0,
      "termMaxMonths": 36
    },
    {
      "id": 38,
      "bank": "中国农业发展银行榕江县支行",
      "name": "涉农普惠小微企业贷款（流动资金贷款）",
      "category": "普惠小微",
      "target": "符合国家统计局关于小型、微型企业划分标准相关规定，且符合监管部门普惠型小微企业贷款标准的经市场监督管理部门或主管机关核准登记的涉农企业法人或农民专业合作社等符合国家规定可以作为借款人的其他经济组织",
      "conditions": "（一）具备合法合规的经营主体资格，营业期限覆盖贷款期限。\n（二）具备从事相关业务的资质和能力。\n（三）经营活动及借款用途符合国家法律、法规要求，符合国家产业政策、环境政策，符合农发行信贷业务支持范围和信贷政策，不涉及高耗能、高排放等不符合国家有关政策要求的情形。\n（四）信用状况良好，近五年无重大或恶意形成的不良信用记录，未涉及恶性刑事案件或对其产生重大不利影响的民事案件。\n（五）生产经营合规正常。具有持续经营能力，有合法的还款来源，具备按期偿还贷款本息的能力。\n（六）反洗钱和反恐怖融资情况符合监管部门和农发行相关管理要求。\n（七）未被纳入农发行行贿人“黑名单”。\n（八）农发行要求的其他条件。",
      "region": "榕江县",
      "guarantee": "保证、抵押、质押",
      "amount": "1000万元",
      "term": "1-3年",
      "rate": "LPR（对普惠小微企业实行减费让利，对国家乡村振兴重点帮扶县的普惠小微企业实行一定的利率优惠，优惠5-10BP。）",
      "process": "客户申请→受理→申报→调查→审查→审批→合同签订→贷款发放\n（使用本产品通过线上途径办理贷款的，借款人登录线上贷款业务服务平台，提交贷款申请，通过风控模型自动化等方式完成客户身份识别、合作机构初审（如需）、农发行审批等贷款办理流程。线上途径办理的贷款，可简化或不再进行现场调查，但应满足农发行线上贷款业务其他相关规定。）",
      "contact": "吴经理0855-6622574",
      "amountMax": 1000.0,
      "termMaxMonths": 36
    }
  ]
}